{"appleSKU":"","appleTeamID":"","enableCodelessAutoInitialization":true,"enableUnityGamingServicesAutoInitialization":true,"products":[{"id":"appname_remove_ads","type":1,"storeIDs":[],"defaultDescription":{"googleLocale":4,"title":"Remove Ads","description":"Remove Ads"},"screenshotPath":"","applePriceTier":3,"googlePrice":{"data":[299,0,0,131072],"num":2.99},"pricingTemplateID":"","descriptions":[],"udpPrice":{"data":[0,0,0,0],"num":0.0},"payouts":[]},{"id":"appname_get_gems_1","type":0,"storeIDs":[],"defaultDescription":{"googleLocale":4,"title":"Get Gems","description":"Get 1000 gems"},"screenshotPath":"","applePriceTier":1,"googlePrice":{"data":[99,0,0,131072],"num":0.99},"pricingTemplateID":"","descriptions":[],"udpPrice":{"data":[0,0,0,0],"num":0.0},"payouts":[{"t":"Other","st":"","q":1000.0,"d":""}]},{"id":"appname_get_gems_2","type":0,"storeIDs":[],"defaultDescription":{"googleLocale":4,"title":"Get Gems","description":"Get 5000 Gems"},"screenshotPath":"","applePriceTier":5,"googlePrice":{"data":[499,0,0,131072],"num":4.99},"pricingTemplateID":"","descriptions":[],"udpPrice":{"data":[0,0,0,0],"num":0.0},"payouts":[{"t":"Other","st":"","q":5000.0,"d":""}]}]}